{
	"usage": "<player> weaponLockFinalize(<entity>)",
	"description": [
		"Locks player's weapon onto an entity. Implies weaponLockStart(), so this may be called to jump to a hard lock.",
		"*🚩 This documentation is for the IW3 version of this function credit to Raid Gaming and has yet to be reviewed/updated for IW4.*"
	],
	"params": [
		{
			"name": "entity",
			"types": ["Entity"],
			"description": ["An entity."],
			"optional": false
		}
	],
	"example": ["level.player weaponLockFinalize(enemyGuy);"]
}
